fooman-0.1.1.dist-info/METADATA
fooman-0.1.1.dist-info/WHEEL
fooman-0.1.1.dist-info/licenses/LICENSE
fooman/__init__.py
fooman/broker.py
fooman/brokers/__init__.py
fooman/brokers/rabbitmq.py
fooman/brokers/redis.py
fooman/client.py
fooman/models.py
fooman/server.py
fooman/types.py
fooman-0.1.1.dist-info/RECORD
