Metadata-Version: 2.1
Name: fooman
Version: 0.1.1
Summary: Boost microservices communication with our powerful async RPC library, featuring seamless integration with popular message brokers like Redis, Kafka, and RabbitMQ.
Author-Email: amirbahador <amirbahador.pv@gmail.com>
License: Apache
Requires-Python: >=3.11
Requires-Dist: aio-pika>=9.4.0
Requires-Dist: redis>=5.0.1
Requires-Dist: pydantic>=2.6.2
